{"object":"card","id":"cd8fffd3-81ad-47e3-a27b-d8059f2b506f","oracle_id":"d4ec0df9-a4a3-48cf-a0aa-b1aea5c49142","multiverse_ids":[386506],"tcgplayer_id":92948,"name":"Clever Impersonator","lang":"en","released_at":"2014-09-26","uri":"https://api.scryfall.com/cards/cd8fffd3-81ad-47e3-a27b-d8059f2b506f","scryfall_uri":"https://scryfall.com/card/ktk/34/clever-impersonator?utm_source=api","layout":"normal","image_uris":{"small":"https://img.scryfall.com/cards/small/front/c/d/cd8fffd3-81ad-47e3-a27b-d8059f2b506f.jpg?1562793709","normal":"https://img.scryfall.com/cards/normal/front/c/d/cd8fffd3-81ad-47e3-a27b-d8059f2b506f.jpg?1562793709","large":"https://img.scryfall.com/cards/large/front/c/d/cd8fffd3-81ad-47e3-a27b-d8059f2b506f.jpg?1562793709","png":"https://img.scryfall.com/cards/png/front/c/d/cd8fffd3-81ad-47e3-a27b-d8059f2b506f.png?1562793709","art_crop":"https://img.scryfall.com/cards/art_crop/front/c/d/cd8fffd3-81ad-47e3-a27b-d8059f2b506f.jpg?1562793709","border_crop":"https://img.scryfall.com/cards/border_crop/front/c/d/cd8fffd3-81ad-47e3-a27b-d8059f2b506f.jpg?1562793709"},"mana_cost":"{2}{U}{U}","cmc":4.0,"type_line":"Creature — Shapeshifter","oracle_text":"You may have Clever Impersonator enter the battlefield as a copy of any nonland permanent on the battlefield.","colors":["U"],"color_identity":["U"],"legalities":{"standard":"not_legal","future":"not_legal","historic":"not_legal","pioneer":"legal","modern":"legal","legacy":"legal","pauper":"not_legal","vintage":"legal","penny":"not_legal","commander":"legal","brawl":"not_legal","duel":"legal","oldschool":"not_legal"},"games":["paper","mtgo"],"set":"ktk","set_name":"Khans of Tarkir","set_type":"expansion","set_uri":"https://api.scryfall.com/sets/6c7a715c-ded9-449e-89b0-c665773e9c3c","set_search_uri":"https://api.scryfall.com/cards/search?order=set&q=e%3Aktk&unique=prints","scryfall_set_uri":"https://scryfall.com/sets/ktk?utm_source=api","rulings_uri":"https://api.scryfall.com/cards/cd8fffd3-81ad-47e3-a27b-d8059f2b506f/rulings","prints_search_uri":"https://api.scryfall.com/cards/search?order=released&q=oracleid%3Ad4ec0df9-a4a3-48cf-a0aa-b1aea5c49142&unique=prints","rarity":"mythic","card_back_id":"0aeebaf5-8c7d-4636-9e82-8c27447861f7","artist":"Slawomir Maniak","artist_ids":["d887bc66-2779-416c-a1ff-d8720242063e"],"illustration_id":"29c743ec-b9ec-4dbf-93ba-786b961fdb45","border_color":"black","frame":"2015","edhrec_rank":412,"related_uris":{"tcgplayer_decks":"https://decks.tcgplayer.com/magic/deck/search?contains=Clever+Impersonator&page=1&partner=Scryfall&utm_campaign=affiliate&utm_medium=api&utm_source=scryfall","edhrec":"https://edhrec.com/route/?cc=Clever+Impersonator","mtgtop8":"https://mtgtop8.com/search?MD_check=1&SB_check=1&cards=Clever+Impersonator"}}