{"object":"card","id":"c7e71299-98f6-494e-b187-8d22ce5f50af","oracle_id":"01546b7d-a233-4176-8843-d732074dc5b6","multiverse_ids":[89116],"tcgplayer_id":13261,"name":"Doubling Season","lang":"en","released_at":"2005-10-07","uri":"https://api.scryfall.com/cards/c7e71299-98f6-494e-b187-8d22ce5f50af","scryfall_uri":"https://scryfall.com/card/rav/158/doubling-season?utm_source=api","layout":"normal","image_uris":{"small":"https://img.scryfall.com/cards/small/front/c/7/c7e71299-98f6-494e-b187-8d22ce5f50af.jpg?1562120759","normal":"https://img.scryfall.com/cards/normal/front/c/7/c7e71299-98f6-494e-b187-8d22ce5f50af.jpg?1562120759","large":"https://img.scryfall.com/cards/large/front/c/7/c7e71299-98f6-494e-b187-8d22ce5f50af.jpg?1562120759","png":"https://img.scryfall.com/cards/png/front/c/7/c7e71299-98f6-494e-b187-8d22ce5f50af.png?1562120759","art_crop":"https://img.scryfall.com/cards/art_crop/front/c/7/c7e71299-98f6-494e-b187-8d22ce5f50af.jpg?1562120759","border_crop":"https://img.scryfall.com/cards/border_crop/front/c/7/c7e71299-98f6-494e-b187-8d22ce5f50af.jpg?1562120759"},"mana_cost":"{4}{G}","cmc":5.0,"type_line":"Enchantment","oracle_text":"If an effect would create one or more tokens under your control, it creates twice that many of those tokens instead.\nIf an effect would put one or more counters on a permanent you control, it puts twice that many of those counters on that permanent instead.","colors":["G"],"color_identity":["G"],"legalities":{"standard":"not_legal","future":"not_legal","historic":"not_legal","pioneer":"not_legal","modern":"legal","legacy":"legal","pauper":"not_legal","vintage":"legal","penny":"not_legal","commander":"legal","brawl":"not_legal","duel":"legal","oldschool":"not_legal"},"games":["paper","mtgo"],"set":"rav","set_name":"Ravnica: City of Guilds","set_type":"expansion","set_uri":"https://api.scryfall.com/sets/15fccbe8-2825-41ca-9d0a-67aebdf91c4a","set_search_uri":"https://api.scryfall.com/cards/search?order=set&q=e%3Arav&unique=prints","scryfall_set_uri":"https://scryfall.com/sets/rav?utm_source=api","rulings_uri":"https://api.scryfall.com/cards/c7e71299-98f6-494e-b187-8d22ce5f50af/rulings","prints_search_uri":"https://api.scryfall.com/cards/search?order=released&q=oracleid%3A01546b7d-a233-4176-8843-d732074dc5b6&unique=prints","rarity":"rare","card_back_id":"0aeebaf5-8c7d-4636-9e82-8c27447861f7","artist":"Wayne Reynolds","artist_ids":["afc47cec-3ccc-404e-a8c6-4d83dd504271"],"illustration_id":"da106099-46e1-4739-88b9-20543678899a","border_color":"black","frame":"2003","edhrec_rank":322,"related_uris":{"tcgplayer_decks":"https://decks.tcgplayer.com/magic/deck/search?contains=Doubling+Season&page=1&partner=Scryfall&utm_campaign=affiliate&utm_medium=api&utm_source=scryfall","edhrec":"https://edhrec.com/route/?cc=Doubling+Season","mtgtop8":"https://mtgtop8.com/search?MD_check=1&SB_check=1&cards=Doubling+Season"}}