{"object":"card","id":"a213450f-02f4-4c08-8da8-891ebfa8e237","oracle_id":"00358a89-2058-448b-a2fd-389f639ba2da","multiverse_ids":[1738],"tcgplayer_id":3551,"name":"Murk Dwellers","lang":"en","released_at":"1994-08-01","uri":"https://api.scryfall.com/cards/a213450f-02f4-4c08-8da8-891ebfa8e237","scryfall_uri":"https://scryfall.com/card/drk/49/murk-dwellers?utm_source=api","layout":"normal","image_uris":{"small":"https://img.scryfall.com/cards/small/front/a/2/a213450f-02f4-4c08-8da8-891ebfa8e237.jpg?1562933265","normal":"https://img.scryfall.com/cards/normal/front/a/2/a213450f-02f4-4c08-8da8-891ebfa8e237.jpg?1562933265","large":"https://img.scryfall.com/cards/large/front/a/2/a213450f-02f4-4c08-8da8-891ebfa8e237.jpg?1562933265","png":"https://img.scryfall.com/cards/png/front/a/2/a213450f-02f4-4c08-8da8-891ebfa8e237.png?1562933265","art_crop":"https://img.scryfall.com/cards/art_crop/front/a/2/a213450f-02f4-4c08-8da8-891ebfa8e237.jpg?1562933265","border_crop":"https://img.scryfall.com/cards/border_crop/front/a/2/a213450f-02f4-4c08-8da8-891ebfa8e237.jpg?1562933265"},"mana_cost":"{3}{B}","cmc":4.0,"type_line":"Creature — Zombie","oracle_text":"Whenever Murk Dwellers attacks and isn't blocked, it gets +2/+0 until end of combat.","colors":["B"],"color_identity":["B"],"legalities":{"standard":"not_legal","future":"not_legal","historic":"not_legal","pioneer":"not_legal","modern":"not_legal","legacy":"legal","pauper":"legal","vintage":"legal","penny":"not_legal","commander":"legal","brawl":"not_legal","duel":"legal","oldschool":"legal"},"games":["paper"],"set":"drk","set_name":"The Dark","set_type":"expansion","set_uri":"https://api.scryfall.com/sets/a21c6836-c435-459a-81e3-22d2da174549","set_search_uri":"https://api.scryfall.com/cards/search?order=set&q=e%3Adrk&unique=prints","scryfall_set_uri":"https://scryfall.com/sets/drk?utm_source=api","rulings_uri":"https://api.scryfall.com/cards/a213450f-02f4-4c08-8da8-891ebfa8e237/rulings","prints_search_uri":"https://api.scryfall.com/cards/search?order=released&q=oracleid%3A00358a89-2058-448b-a2fd-389f639ba2da&unique=prints","rarity":"common","card_back_id":"0aeebaf5-8c7d-4636-9e82-8c27447861f7","artist":"Drew Tucker","artist_ids":["22eef389-7b21-4dda-95dc-4c9a0f1bf4dd"],"illustration_id":"1ac49fa3-1963-4af3-852a-b98fe3a1633d","border_color":"black","frame":"1993","edhrec_rank":19502,"related_uris":{"tcgplayer_decks":"https://decks.tcgplayer.com/magic/deck/search?contains=Murk+Dwellers&page=1&partner=Scryfall&utm_campaign=affiliate&utm_medium=api&utm_source=scryfall","edhrec":"https://edhrec.com/route/?cc=Murk+Dwellers","mtgtop8":"https://mtgtop8.com/search?MD_check=1&SB_check=1&cards=Murk+Dwellers"}}