{"object":"card","id":"d53ee8c0-b27c-4556-b610-ff64edb7a18f","oracle_id":"7dec219b-96d1-4d4c-b3ac-15eda9d2ccc6","multiverse_ids":[445974],"tcgplayer_id":167828,"name":"Okaun, Eye of Chaos","lang":"en","released_at":"2018-06-08","uri":"https://api.scryfall.com/cards/d53ee8c0-b27c-4556-b610-ff64edb7a18f","scryfall_uri":"https://scryfall.com/card/bbd/6/okaun-eye-of-chaos?utm_source=api","layout":"normal","image_uris":{"small":"https://img.scryfall.com/cards/small/front/d/5/d53ee8c0-b27c-4556-b610-ff64edb7a18f.jpg?1562937757","normal":"https://img.scryfall.com/cards/normal/front/d/5/d53ee8c0-b27c-4556-b610-ff64edb7a18f.jpg?1562937757","large":"https://img.scryfall.com/cards/large/front/d/5/d53ee8c0-b27c-4556-b610-ff64edb7a18f.jpg?1562937757","png":"https://img.scryfall.com/cards/png/front/d/5/d53ee8c0-b27c-4556-b610-ff64edb7a18f.png?1562937757","art_crop":"https://img.scryfall.com/cards/art_crop/front/d/5/d53ee8c0-b27c-4556-b610-ff64edb7a18f.jpg?1562937757","border_crop":"https://img.scryfall.com/cards/border_crop/front/d/5/d53ee8c0-b27c-4556-b610-ff64edb7a18f.jpg?1562937757"},"mana_cost":"{4}{R}","cmc":5.0,"type_line":"Legendary Creature — Cyclops Berserker","oracle_text":"Partner with Zndrsplt, Eye of Wisdom (When this creature enters the battlefield, target player may put Zndrsplt into their hand from their library, then shuffle.)\nAt the beginning of combat on your turn, flip a coin until you lose a flip.\nWhenever a player wins a coin flip, double Okaun's power and toughness until end of turn.","colors":["R"],"color_identity":["R"],"legalities":{"standard":"not_legal","future":"not_legal","historic":"not_legal","pioneer":"not_legal","modern":"not_legal","legacy":"legal","pauper":"not_legal","vintage":"legal","penny":"not_legal","commander":"legal","brawl":"not_legal","duel":"legal","oldschool":"not_legal"},"games":["paper","mtgo"],"set":"bbd","set_name":"Battlebond","set_type":"draft_innovation","set_uri":"https://api.scryfall.com/sets/95f97fbc-58ef-4645-982e-43e2db6f1124","set_search_uri":"https://api.scryfall.com/cards/search?order=set&q=e%3Abbd&unique=prints","scryfall_set_uri":"https://scryfall.com/sets/bbd?utm_source=api","rulings_uri":"https://api.scryfall.com/cards/d53ee8c0-b27c-4556-b610-ff64edb7a18f/rulings","prints_search_uri":"https://api.scryfall.com/cards/search?order=released&q=oracleid%3A7dec219b-96d1-4d4c-b3ac-15eda9d2ccc6&unique=prints","rarity":"rare","card_back_id":"0aeebaf5-8c7d-4636-9e82-8c27447861f7","artist":"Yongjae Choi","artist_ids":["5ab91c3b-a6da-4751-a56e-81d0f61a67ab"],"illustration_id":"4922f53b-bdc9-439f-be15-89a420b6ffaa","border_color":"black","frame":"2015","edhrec_rank":4726,"related_uris":{"tcgplayer_decks":"https://decks.tcgplayer.com/magic/deck/search?contains=Okaun%2C+Eye+of+Chaos&page=1&partner=Scryfall&utm_campaign=affiliate&utm_medium=api&utm_source=scryfall","edhrec":"https://edhrec.com/route/?cc=Okaun%2C+Eye+of+Chaos","mtgtop8":"https://mtgtop8.com/search?MD_check=1&SB_check=1&cards=Okaun%2C+Eye+of+Chaos"}}