{"object":"card","id":"a232d196-490d-4712-b2a2-466751b28d11","oracle_id":"00bcfbaf-cd31-4688-973e-4238749051b7","multiverse_ids":[386710],"tcgplayer_id":93249,"name":"Unyielding Krumar","lang":"en","released_at":"2014-09-26","uri":"https://api.scryfall.com/cards/a232d196-490d-4712-b2a2-466751b28d11","scryfall_uri":"https://scryfall.com/card/ktk/94/unyielding-krumar?utm_source=api","layout":"normal","image_uris":{"small":"https://img.scryfall.com/cards/small/front/a/2/a232d196-490d-4712-b2a2-466751b28d11.jpg?1562791316","normal":"https://img.scryfall.com/cards/normal/front/a/2/a232d196-490d-4712-b2a2-466751b28d11.jpg?1562791316","large":"https://img.scryfall.com/cards/large/front/a/2/a232d196-490d-4712-b2a2-466751b28d11.jpg?1562791316","png":"https://img.scryfall.com/cards/png/front/a/2/a232d196-490d-4712-b2a2-466751b28d11.png?1562791316","art_crop":"https://img.scryfall.com/cards/art_crop/front/a/2/a232d196-490d-4712-b2a2-466751b28d11.jpg?1562791316","border_crop":"https://img.scryfall.com/cards/border_crop/front/a/2/a232d196-490d-4712-b2a2-466751b28d11.jpg?1562791316"},"mana_cost":"{3}{B}","cmc":4.0,"type_line":"Creature — Orc Warrior","oracle_text":"{1}{W}: Unyielding Krumar gains first strike until end of turn.","colors":["B"],"color_identity":["B","W"],"legalities":{"standard":"not_legal","future":"not_legal","historic":"not_legal","pioneer":"legal","modern":"legal","legacy":"legal","pauper":"legal","vintage":"legal","penny":"legal","commander":"legal","brawl":"not_legal","duel":"legal","oldschool":"not_legal"},"games":["paper","mtgo"],"set":"ktk","set_name":"Khans of Tarkir","set_type":"expansion","set_uri":"https://api.scryfall.com/sets/6c7a715c-ded9-449e-89b0-c665773e9c3c","set_search_uri":"https://api.scryfall.com/cards/search?order=set&q=e%3Aktk&unique=prints","scryfall_set_uri":"https://scryfall.com/sets/ktk?utm_source=api","rulings_uri":"https://api.scryfall.com/cards/a232d196-490d-4712-b2a2-466751b28d11/rulings","prints_search_uri":"https://api.scryfall.com/cards/search?order=released&q=oracleid%3A00bcfbaf-cd31-4688-973e-4238749051b7&unique=prints","rarity":"common","card_back_id":"0aeebaf5-8c7d-4636-9e82-8c27447861f7","artist":"Viktor Titov","artist_ids":["2270c0b0-afb4-42b0-bcb6-25fe4ad6eef2"],"illustration_id":"834e26ac-312f-4679-8cc5-ec1e7621ff0e","border_color":"black","frame":"2015","edhrec_rank":15918,"related_uris":{"tcgplayer_decks":"https://decks.tcgplayer.com/magic/deck/search?contains=Unyielding+Krumar&page=1&partner=Scryfall&utm_campaign=affiliate&utm_medium=api&utm_source=scryfall","edhrec":"https://edhrec.com/route/?cc=Unyielding+Krumar","mtgtop8":"https://mtgtop8.com/search?MD_check=1&SB_check=1&cards=Unyielding+Krumar"}}