{"object":"card","id":"f2d9b77b-d775-4546-91c8-df438a1d8dbe","oracle_id":"2a93236d-f182-4826-8112-4048bb3cbaf9","multiverse_ids":[46148],"tcgplayer_id":11606,"name":"Ageless Entity","lang":"en","released_at":"2004-02-06","uri":"https://api.scryfall.com/cards/f2d9b77b-d775-4546-91c8-df438a1d8dbe","scryfall_uri":"https://scryfall.com/card/dst/73/ageless-entity?utm_source=api","layout":"normal","image_uris":{"small":"https://img.scryfall.com/cards/small/front/f/2/f2d9b77b-d775-4546-91c8-df438a1d8dbe.jpg?1562640438","normal":"https://img.scryfall.com/cards/normal/front/f/2/f2d9b77b-d775-4546-91c8-df438a1d8dbe.jpg?1562640438","large":"https://img.scryfall.com/cards/large/front/f/2/f2d9b77b-d775-4546-91c8-df438a1d8dbe.jpg?1562640438","png":"https://img.scryfall.com/cards/png/front/f/2/f2d9b77b-d775-4546-91c8-df438a1d8dbe.png?1562640438","art_crop":"https://img.scryfall.com/cards/art_crop/front/f/2/f2d9b77b-d775-4546-91c8-df438a1d8dbe.jpg?1562640438","border_crop":"https://img.scryfall.com/cards/border_crop/front/f/2/f2d9b77b-d775-4546-91c8-df438a1d8dbe.jpg?1562640438"},"mana_cost":"{3}{G}{G}","cmc":5.0,"type_line":"Creature — Elemental","oracle_text":"Whenever you gain life, put that many +1/+1 counters on Ageless Entity.","colors":["G"],"color_identity":["G"],"legalities":{"standard":"not_legal","future":"not_legal","historic":"not_legal","pioneer":"not_legal","modern":"legal","legacy":"legal","pauper":"not_legal","vintage":"legal","penny":"not_legal","commander":"legal","brawl":"not_legal","duel":"legal","oldschool":"not_legal"},"games":["paper","mtgo"],"set":"dst","set_name":"Darksteel","set_type":"expansion","set_uri":"https://api.scryfall.com/sets/e29cb2dd-1345-4032-abfe-e52e8c8ce074","set_search_uri":"https://api.scryfall.com/cards/search?order=set&q=e%3Adst&unique=prints","scryfall_set_uri":"https://scryfall.com/sets/dst?utm_source=api","rulings_uri":"https://api.scryfall.com/cards/f2d9b77b-d775-4546-91c8-df438a1d8dbe/rulings","prints_search_uri":"https://api.scryfall.com/cards/search?order=released&q=oracleid%3A2a93236d-f182-4826-8112-4048bb3cbaf9&unique=prints","rarity":"rare","card_back_id":"0aeebaf5-8c7d-4636-9e82-8c27447861f7","artist":"Jeff Miracola","artist_ids":["9b465bde-3656-4495-ace4-af4ce29999ed"],"illustration_id":"7d1a7b55-813f-4083-943a-8084e0464c66","border_color":"black","frame":"2003","edhrec_rank":8597,"related_uris":{"tcgplayer_decks":"https://decks.tcgplayer.com/magic/deck/search?contains=Ageless+Entity&page=1&partner=Scryfall&utm_campaign=affiliate&utm_medium=api&utm_source=scryfall","edhrec":"https://edhrec.com/route/?cc=Ageless+Entity","mtgtop8":"https://mtgtop8.com/search?MD_check=1&SB_check=1&cards=Ageless+Entity"}}