{"object":"card","id":"e24d4fba-cf12-4ad3-bca3-6824dbc639af","oracle_id":"53d0720d-a2dc-418f-94cc-f150fa47d23f","multiverse_ids":[9747],"tcgplayer_id":835,"name":"Censorship","lang":"en","released_at":"1998-08-11","uri":"https://api.scryfall.com/cards/e24d4fba-cf12-4ad3-bca3-6824dbc639af","scryfall_uri":"https://scryfall.com/card/ugl/15/censorship?utm_source=api","layout":"normal","image_uris":{"small":"https://img.scryfall.com/cards/small/front/e/2/e24d4fba-cf12-4ad3-bca3-6824dbc639af.jpg?1562799173","normal":"https://img.scryfall.com/cards/normal/front/e/2/e24d4fba-cf12-4ad3-bca3-6824dbc639af.jpg?1562799173","large":"https://img.scryfall.com/cards/large/front/e/2/e24d4fba-cf12-4ad3-bca3-6824dbc639af.jpg?1562799173","png":"https://img.scryfall.com/cards/png/front/e/2/e24d4fba-cf12-4ad3-bca3-6824dbc639af.png?1562799173","art_crop":"https://img.scryfall.com/cards/art_crop/front/e/2/e24d4fba-cf12-4ad3-bca3-6824dbc639af.jpg?1562799173","border_crop":"https://img.scryfall.com/cards/border_crop/front/e/2/e24d4fba-cf12-4ad3-bca3-6824dbc639af.jpg?1562799173"},"mana_cost":"{U}","cmc":1.0,"type_line":"Enchantment","oracle_text":"As Censorship enters the battlefield, choose a word.\nWhenever a player says the chosen word, Censorship deals 2 damage to that player.","colors":["U"],"color_identity":["U"],"legalities":{"standard":"not_legal","future":"not_legal","historic":"not_legal","pioneer":"not_legal","modern":"not_legal","legacy":"not_legal","pauper":"not_legal","vintage":"not_legal","penny":"not_legal","commander":"not_legal","brawl":"not_legal","duel":"not_legal","oldschool":"not_legal"},"games":["paper"],"set":"ugl","set_name":"Unglued","set_type":"funny","set_uri":"https://api.scryfall.com/sets/3404fc78-6678-4cf4-bd39-4c0be3bb7baf","set_search_uri":"https://api.scryfall.com/cards/search?order=set&q=e%3Augl&unique=prints","scryfall_set_uri":"https://scryfall.com/sets/ugl?utm_source=api","rulings_uri":"https://api.scryfall.com/cards/e24d4fba-cf12-4ad3-bca3-6824dbc639af/rulings","prints_search_uri":"https://api.scryfall.com/cards/search?order=released&q=oracleid%3A53d0720d-a2dc-418f-94cc-f150fa47d23f&unique=prints","rarity":"uncommon","card_back_id":"0aeebaf5-8c7d-4636-9e82-8c27447861f7","artist":"Matthew D. Wilson","artist_ids":["4fbafd13-0cf9-42a1-870d-7f8ea276f140"],"illustration_id":"fde5c8a5-9382-4086-9b11-48081c68a51a","border_color":"silver","frame":"1997","edhrec_rank":0,"related_uris":{"tcgplayer_decks":"https://decks.tcgplayer.com/magic/deck/search?contains=Censorship&page=1&partner=Scryfall&utm_campaign=affiliate&utm_medium=api&utm_source=scryfall","edhrec":"https://edhrec.com/route/?cc=Censorship","mtgtop8":"https://mtgtop8.com/search?MD_check=1&SB_check=1&cards=Censorship"}}