{"object":"card","id":"312a6058-de08-487d-95bd-b3c56807fdd6","oracle_id":"33c722cf-b4bf-431f-aefd-ee96241a7fbf","multiverse_ids":[51133],"tcgplayer_id":11791,"name":"Crucible of Worlds","lang":"en","released_at":"2004-06-04","uri":"https://api.scryfall.com/cards/312a6058-de08-487d-95bd-b3c56807fdd6","scryfall_uri":"https://scryfall.com/card/5dn/114/crucible-of-worlds?utm_source=api","layout":"normal","image_uris":{"small":"https://img.scryfall.com/cards/small/front/3/1/312a6058-de08-487d-95bd-b3c56807fdd6.jpg?1562876165","normal":"https://img.scryfall.com/cards/normal/front/3/1/312a6058-de08-487d-95bd-b3c56807fdd6.jpg?1562876165","large":"https://img.scryfall.com/cards/large/front/3/1/312a6058-de08-487d-95bd-b3c56807fdd6.jpg?1562876165","png":"https://img.scryfall.com/cards/png/front/3/1/312a6058-de08-487d-95bd-b3c56807fdd6.png?1562876165","art_crop":"https://img.scryfall.com/cards/art_crop/front/3/1/312a6058-de08-487d-95bd-b3c56807fdd6.jpg?1562876165","border_crop":"https://img.scryfall.com/cards/border_crop/front/3/1/312a6058-de08-487d-95bd-b3c56807fdd6.jpg?1562876165"},"mana_cost":"{3}","cmc":3.0,"type_line":"Artifact","oracle_text":"You may play land cards from your graveyard.","colors":[],"color_identity":[],"legalities":{"standard":"not_legal","future":"not_legal","historic":"legal","pioneer":"legal","modern":"legal","legacy":"legal","pauper":"not_legal","vintage":"legal","penny":"not_legal","commander":"legal","brawl":"not_legal","duel":"legal","oldschool":"not_legal"},"games":["paper","mtgo"],"set":"5dn","set_name":"Fifth Dawn","set_type":"expansion","set_uri":"https://api.scryfall.com/sets/e4bc1b87-5476-463c-8640-4c414ecf1763","set_search_uri":"https://api.scryfall.com/cards/search?order=set&q=e%3A5dn&unique=prints","scryfall_set_uri":"https://scryfall.com/sets/5dn?utm_source=api","rulings_uri":"https://api.scryfall.com/cards/312a6058-de08-487d-95bd-b3c56807fdd6/rulings","prints_search_uri":"https://api.scryfall.com/cards/search?order=released&q=oracleid%3A33c722cf-b4bf-431f-aefd-ee96241a7fbf&unique=prints","rarity":"rare","card_back_id":"0aeebaf5-8c7d-4636-9e82-8c27447861f7","artist":"Ron Spencer","artist_ids":["dab52c11-0564-4207-a4a1-c1735c946a65"],"illustration_id":"3dba8aff-0042-4369-b1ef-93e0005cba85","border_color":"black","frame":"2003","edhrec_rank":243,"related_uris":{"tcgplayer_decks":"https://decks.tcgplayer.com/magic/deck/search?contains=Crucible+of+Worlds&page=1&partner=Scryfall&utm_campaign=affiliate&utm_medium=api&utm_source=scryfall","edhrec":"https://edhrec.com/route/?cc=Crucible+of+Worlds","mtgtop8":"https://mtgtop8.com/search?MD_check=1&SB_check=1&cards=Crucible+of+Worlds"}}