{"object":"card","id":"f11684d6-5b74-47a7-a2d0-256c9e437aa6","oracle_id":"fc9e82b2-f148-431b-9312-97b7101cffe4","multiverse_ids":[942],"tcgplayer_id":3177,"name":"Cyclone","lang":"en","released_at":"1993-12-17","uri":"https://api.scryfall.com/cards/f11684d6-5b74-47a7-a2d0-256c9e437aa6","scryfall_uri":"https://scryfall.com/card/arn/45/cyclone?utm_source=api","layout":"normal","image_uris":{"small":"https://img.scryfall.com/cards/small/front/f/1/f11684d6-5b74-47a7-a2d0-256c9e437aa6.jpg?1562940349","normal":"https://img.scryfall.com/cards/normal/front/f/1/f11684d6-5b74-47a7-a2d0-256c9e437aa6.jpg?1562940349","large":"https://img.scryfall.com/cards/large/front/f/1/f11684d6-5b74-47a7-a2d0-256c9e437aa6.jpg?1562940349","png":"https://img.scryfall.com/cards/png/front/f/1/f11684d6-5b74-47a7-a2d0-256c9e437aa6.png?1562940349","art_crop":"https://img.scryfall.com/cards/art_crop/front/f/1/f11684d6-5b74-47a7-a2d0-256c9e437aa6.jpg?1562940349","border_crop":"https://img.scryfall.com/cards/border_crop/front/f/1/f11684d6-5b74-47a7-a2d0-256c9e437aa6.jpg?1562940349"},"mana_cost":"{2}{G}{G}","cmc":4.0,"type_line":"Enchantment","oracle_text":"At the beginning of your upkeep, put a wind counter on Cyclone, then sacrifice Cyclone unless you pay {G} for each wind counter on it. If you pay, Cyclone deals damage equal to the number of wind counters on it to each creature and each player.","colors":["G"],"color_identity":["G"],"legalities":{"standard":"not_legal","future":"not_legal","historic":"not_legal","pioneer":"not_legal","modern":"not_legal","legacy":"legal","pauper":"not_legal","vintage":"legal","penny":"not_legal","commander":"legal","brawl":"not_legal","duel":"legal","oldschool":"legal"},"games":["paper"],"set":"arn","set_name":"Arabian Nights","set_type":"expansion","set_uri":"https://api.scryfall.com/sets/856f63eb-e056-43e5-8a56-7a58e1608940","set_search_uri":"https://api.scryfall.com/cards/search?order=set&q=e%3Aarn&unique=prints","scryfall_set_uri":"https://scryfall.com/sets/arn?utm_source=api","rulings_uri":"https://api.scryfall.com/cards/f11684d6-5b74-47a7-a2d0-256c9e437aa6/rulings","prints_search_uri":"https://api.scryfall.com/cards/search?order=released&q=oracleid%3Afc9e82b2-f148-431b-9312-97b7101cffe4&unique=prints","rarity":"uncommon","card_back_id":"0aeebaf5-8c7d-4636-9e82-8c27447861f7","artist":"Mark Tedin","artist_ids":["9ee9a9cc-c09e-486f-918b-69f80cbc4188"],"illustration_id":"14232b8b-0569-45bb-bb8d-ac8ce0b81c35","border_color":"black","frame":"1993","edhrec_rank":12958,"related_uris":{"tcgplayer_decks":"https://decks.tcgplayer.com/magic/deck/search?contains=Cyclone&page=1&partner=Scryfall&utm_campaign=affiliate&utm_medium=api&utm_source=scryfall","edhrec":"https://edhrec.com/route/?cc=Cyclone","mtgtop8":"https://mtgtop8.com/search?MD_check=1&SB_check=1&cards=Cyclone"}}