{"object":"card","id":"445127d4-8afb-47cf-b2a1-564540b1fdae","oracle_id":"87f82107-eaba-484a-800d-e61a0cc5e1f2","multiverse_ids":[26259],"tcgplayer_id":7937,"name":"Desolation Angel","lang":"en","released_at":"2001-06-04","uri":"https://api.scryfall.com/cards/445127d4-8afb-47cf-b2a1-564540b1fdae","scryfall_uri":"https://scryfall.com/card/apc/38/desolation-angel?utm_source=api","layout":"normal","image_uris":{"small":"https://img.scryfall.com/cards/small/front/4/4/445127d4-8afb-47cf-b2a1-564540b1fdae.jpg?1562910998","normal":"https://img.scryfall.com/cards/normal/front/4/4/445127d4-8afb-47cf-b2a1-564540b1fdae.jpg?1562910998","large":"https://img.scryfall.com/cards/large/front/4/4/445127d4-8afb-47cf-b2a1-564540b1fdae.jpg?1562910998","png":"https://img.scryfall.com/cards/png/front/4/4/445127d4-8afb-47cf-b2a1-564540b1fdae.png?1562910998","art_crop":"https://img.scryfall.com/cards/art_crop/front/4/4/445127d4-8afb-47cf-b2a1-564540b1fdae.jpg?1562910998","border_crop":"https://img.scryfall.com/cards/border_crop/front/4/4/445127d4-8afb-47cf-b2a1-564540b1fdae.jpg?1562910998"},"mana_cost":"{3}{B}{B}","cmc":5.0,"type_line":"Creature — Angel","oracle_text":"Kicker {W}{W} (You may pay an additional {W}{W} as you cast this spell.)\nFlying\nWhen Desolation Angel enters the battlefield, destroy all lands you control. If it was kicked, destroy all lands instead.","colors":["B"],"color_identity":["B","W"],"legalities":{"standard":"not_legal","future":"not_legal","historic":"not_legal","pioneer":"not_legal","modern":"not_legal","legacy":"legal","pauper":"not_legal","vintage":"legal","penny":"not_legal","commander":"legal","brawl":"not_legal","duel":"legal","oldschool":"not_legal"},"games":["paper","mtgo"],"set":"apc","set_name":"Apocalypse","set_type":"expansion","set_uri":"https://api.scryfall.com/sets/e4e00913-d08d-4899-86ea-5cf631e09ce0","set_search_uri":"https://api.scryfall.com/cards/search?order=set&q=e%3Aapc&unique=prints","scryfall_set_uri":"https://scryfall.com/sets/apc?utm_source=api","rulings_uri":"https://api.scryfall.com/cards/445127d4-8afb-47cf-b2a1-564540b1fdae/rulings","prints_search_uri":"https://api.scryfall.com/cards/search?order=released&q=oracleid%3A87f82107-eaba-484a-800d-e61a0cc5e1f2&unique=prints","rarity":"rare","card_back_id":"0aeebaf5-8c7d-4636-9e82-8c27447861f7","artist":"Brom","artist_ids":["bd79c951-2552-45dd-aae7-a333c2b7c1ef"],"illustration_id":"0ee477ef-7cbb-45c4-a7b3-1e5977adcc1e","border_color":"black","frame":"1997","edhrec_rank":9735,"related_uris":{"tcgplayer_decks":"https://decks.tcgplayer.com/magic/deck/search?contains=Desolation+Angel&page=1&partner=Scryfall&utm_campaign=affiliate&utm_medium=api&utm_source=scryfall","edhrec":"https://edhrec.com/route/?cc=Desolation+Angel","mtgtop8":"https://mtgtop8.com/search?MD_check=1&SB_check=1&cards=Desolation+Angel"}}