{"object":"card","id":"9ec8db01-415e-42a1-8eb2-57280d58b38e","oracle_id":"3289539e-51eb-4915-bd77-3ac362136f2a","multiverse_ids":[423777],"tcgplayer_id":126489,"name":"Hidden Herbalists","lang":"en","released_at":"2017-01-20","uri":"https://api.scryfall.com/cards/9ec8db01-415e-42a1-8eb2-57280d58b38e","scryfall_uri":"https://scryfall.com/card/aer/110/hidden-herbalists?utm_source=api","layout":"normal","image_uris":{"small":"https://img.scryfall.com/cards/small/front/9/e/9ec8db01-415e-42a1-8eb2-57280d58b38e.jpg?1576381990","normal":"https://img.scryfall.com/cards/normal/front/9/e/9ec8db01-415e-42a1-8eb2-57280d58b38e.jpg?1576381990","large":"https://img.scryfall.com/cards/large/front/9/e/9ec8db01-415e-42a1-8eb2-57280d58b38e.jpg?1576381990","png":"https://img.scryfall.com/cards/png/front/9/e/9ec8db01-415e-42a1-8eb2-57280d58b38e.png?1576381990","art_crop":"https://img.scryfall.com/cards/art_crop/front/9/e/9ec8db01-415e-42a1-8eb2-57280d58b38e.jpg?1576381990","border_crop":"https://img.scryfall.com/cards/border_crop/front/9/e/9ec8db01-415e-42a1-8eb2-57280d58b38e.jpg?1576381990"},"mana_cost":"{1}{G}","cmc":2.0,"type_line":"Creature — Human Druid","oracle_text":"Revolt — When Hidden Herbalists enters the battlefield, if a permanent you controlled left the battlefield this turn, add {G}{G}.","colors":["G"],"color_identity":["G"],"legalities":{"standard":"not_legal","future":"not_legal","historic":"not_legal","pioneer":"legal","modern":"legal","legacy":"legal","pauper":"not_legal","vintage":"legal","penny":"not_legal","commander":"legal","brawl":"not_legal","duel":"legal","oldschool":"not_legal"},"games":["paper","mtgo"],"set":"aer","set_name":"Aether Revolt","set_type":"expansion","set_uri":"https://api.scryfall.com/sets/a4a0db50-8826-4e73-833c-3fd934375f96","set_search_uri":"https://api.scryfall.com/cards/search?order=set&q=e%3Aaer&unique=prints","scryfall_set_uri":"https://scryfall.com/sets/aer?utm_source=api","rulings_uri":"https://api.scryfall.com/cards/9ec8db01-415e-42a1-8eb2-57280d58b38e/rulings","prints_search_uri":"https://api.scryfall.com/cards/search?order=released&q=oracleid%3A3289539e-51eb-4915-bd77-3ac362136f2a&unique=prints","rarity":"uncommon","card_back_id":"0aeebaf5-8c7d-4636-9e82-8c27447861f7","artist":"Bastien L. Deharme","artist_ids":["798f63ec-41ad-474e-9708-df08193345c6"],"illustration_id":"53db12e2-1967-4073-a32b-7bc1d5166804","border_color":"black","frame":"2015","edhrec_rank":13061,"related_uris":{"tcgplayer_decks":"https://decks.tcgplayer.com/magic/deck/search?contains=Hidden+Herbalists&page=1&partner=Scryfall&utm_campaign=affiliate&utm_medium=api&utm_source=scryfall","edhrec":"https://edhrec.com/route/?cc=Hidden+Herbalists","mtgtop8":"https://mtgtop8.com/search?MD_check=1&SB_check=1&cards=Hidden+Herbalists"}}