{"object":"card","id":"9bb0ee6a-852a-4f1e-8f03-40b6d505bc82","oracle_id":"a698c9f5-325a-49f6-8902-eef09f4260c5","multiverse_ids":[191557],"tcgplayer_id":34399,"name":"Lodestone Golem","lang":"en","released_at":"2010-02-05","uri":"https://api.scryfall.com/cards/9bb0ee6a-852a-4f1e-8f03-40b6d505bc82","scryfall_uri":"https://scryfall.com/card/wwk/127/lodestone-golem?utm_source=api","layout":"normal","image_uris":{"small":"https://img.scryfall.com/cards/small/front/9/b/9bb0ee6a-852a-4f1e-8f03-40b6d505bc82.jpg?1562292554","normal":"https://img.scryfall.com/cards/normal/front/9/b/9bb0ee6a-852a-4f1e-8f03-40b6d505bc82.jpg?1562292554","large":"https://img.scryfall.com/cards/large/front/9/b/9bb0ee6a-852a-4f1e-8f03-40b6d505bc82.jpg?1562292554","png":"https://img.scryfall.com/cards/png/front/9/b/9bb0ee6a-852a-4f1e-8f03-40b6d505bc82.png?1562292554","art_crop":"https://img.scryfall.com/cards/art_crop/front/9/b/9bb0ee6a-852a-4f1e-8f03-40b6d505bc82.jpg?1562292554","border_crop":"https://img.scryfall.com/cards/border_crop/front/9/b/9bb0ee6a-852a-4f1e-8f03-40b6d505bc82.jpg?1562292554"},"mana_cost":"{4}","cmc":4.0,"type_line":"Artifact Creature — Golem","oracle_text":"Nonartifact spells cost {1} more to cast.","colors":[],"color_identity":[],"legalities":{"standard":"not_legal","future":"not_legal","historic":"not_legal","pioneer":"not_legal","modern":"legal","legacy":"legal","pauper":"not_legal","vintage":"restricted","penny":"not_legal","commander":"legal","brawl":"not_legal","duel":"legal","oldschool":"not_legal"},"games":["paper","mtgo"],"set":"wwk","set_name":"Worldwake","set_type":"expansion","set_uri":"https://api.scryfall.com/sets/2f248ce6-c2a5-4c6f-a2be-0c593fbe173c","set_search_uri":"https://api.scryfall.com/cards/search?order=set&q=e%3Awwk&unique=prints","scryfall_set_uri":"https://scryfall.com/sets/wwk?utm_source=api","rulings_uri":"https://api.scryfall.com/cards/9bb0ee6a-852a-4f1e-8f03-40b6d505bc82/rulings","prints_search_uri":"https://api.scryfall.com/cards/search?order=released&q=oracleid%3Aa698c9f5-325a-49f6-8902-eef09f4260c5&unique=prints","rarity":"rare","card_back_id":"0aeebaf5-8c7d-4636-9e82-8c27447861f7","artist":"Chris Rahn","artist_ids":["7742047e-0f80-4c0f-a530-d07460165e86"],"illustration_id":"1311e0dd-56ba-40af-b173-b06915182001","border_color":"black","frame":"2003","edhrec_rank":2922,"related_uris":{"tcgplayer_decks":"https://decks.tcgplayer.com/magic/deck/search?contains=Lodestone+Golem&page=1&partner=Scryfall&utm_campaign=affiliate&utm_medium=api&utm_source=scryfall","edhrec":"https://edhrec.com/route/?cc=Lodestone+Golem","mtgtop8":"https://mtgtop8.com/search?MD_check=1&SB_check=1&cards=Lodestone+Golem"}}