{"object":"card","id":"55237cdf-2a83-4467-abc0-f7d8bdcb4b62","oracle_id":"d6912f52-e478-4cc6-a34c-67e372abc4fa","multiverse_ids":[],"tcgplayer_id":0,"name":"Plagued Rusalka","lang":"es","released_at":"2005-08-22","uri":"https://api.scryfall.com/cards/55237cdf-2a83-4467-abc0-f7d8bdcb4b62","scryfall_uri":"https://scryfall.com/card/psal/F28/es/rusalka-infectada?utm_source=api","layout":"normal","image_uris":{"small":"https://img.scryfall.com/cards/small/front/5/5/55237cdf-2a83-4467-abc0-f7d8bdcb4b62.jpg?1562067222","normal":"https://img.scryfall.com/cards/normal/front/5/5/55237cdf-2a83-4467-abc0-f7d8bdcb4b62.jpg?1562067222","large":"https://img.scryfall.com/cards/large/front/5/5/55237cdf-2a83-4467-abc0-f7d8bdcb4b62.jpg?1562067222","png":"https://img.scryfall.com/cards/png/front/5/5/55237cdf-2a83-4467-abc0-f7d8bdcb4b62.png?1562067222","art_crop":"https://img.scryfall.com/cards/art_crop/front/5/5/55237cdf-2a83-4467-abc0-f7d8bdcb4b62.jpg?1562067222","border_crop":"https://img.scryfall.com/cards/border_crop/front/5/5/55237cdf-2a83-4467-abc0-f7d8bdcb4b62.jpg?1562067222"},"mana_cost":"{B}","cmc":1.0,"type_line":"Creature — Spirit","oracle_text":"{B}, Sacrifice a creature: Target creature gets -1/-1 until end of turn.","colors":["B"],"color_identity":["B"],"legalities":{"standard":"not_legal","future":"not_legal","historic":"not_legal","pioneer":"not_legal","modern":"legal","legacy":"legal","pauper":"legal","vintage":"legal","penny":"legal","commander":"legal","brawl":"not_legal","duel":"legal","oldschool":"not_legal"},"games":["paper"],"set":"psal","set_name":"Salvat 2005","set_type":"box","set_uri":"https://api.scryfall.com/sets/1132e6a3-d93a-4ed1-8724-ad5e8e5a1d41","set_search_uri":"https://api.scryfall.com/cards/search?order=set&q=e%3Apsal&unique=prints","scryfall_set_uri":"https://scryfall.com/sets/psal?utm_source=api","rulings_uri":"https://api.scryfall.com/cards/55237cdf-2a83-4467-abc0-f7d8bdcb4b62/rulings","prints_search_uri":"https://api.scryfall.com/cards/search?order=released&q=oracleid%3Ad6912f52-e478-4cc6-a34c-67e372abc4fa&unique=prints","rarity":"uncommon","card_back_id":"0aeebaf5-8c7d-4636-9e82-8c27447861f7","artist":"Alex Horley-Orlandelli","artist_ids":["1631a2ad-bf03-4ab9-b86c-60da982d58a1"],"illustration_id":"5297ffef-fa1f-4e0f-930f-f2867cae4850","border_color":"white","frame":"2003","edhrec_rank":8275,"related_uris":{"tcgplayer_decks":"https://decks.tcgplayer.com/magic/deck/search?contains=Plagued+Rusalka&page=1&partner=Scryfall&utm_campaign=affiliate&utm_medium=api&utm_source=scryfall","edhrec":"https://edhrec.com/route/?cc=Plagued+Rusalka","mtgtop8":"https://mtgtop8.com/search?MD_check=1&SB_check=1&cards=Plagued+Rusalka"}}