{"object":"card","id":"7cff0dc6-5455-4dea-940b-dff7fe88dc5d","oracle_id":"761021ce-4559-464e-aa03-85c2fe78e267","multiverse_ids":[423789],"tcgplayer_id":126363,"name":"Rishkar, Peema Renegade","lang":"en","released_at":"2017-01-20","uri":"https://api.scryfall.com/cards/7cff0dc6-5455-4dea-940b-dff7fe88dc5d","scryfall_uri":"https://scryfall.com/card/aer/122/rishkar-peema-renegade?utm_source=api","layout":"normal","image_uris":{"small":"https://img.scryfall.com/cards/small/front/7/c/7cff0dc6-5455-4dea-940b-dff7fe88dc5d.jpg?1576382069","normal":"https://img.scryfall.com/cards/normal/front/7/c/7cff0dc6-5455-4dea-940b-dff7fe88dc5d.jpg?1576382069","large":"https://img.scryfall.com/cards/large/front/7/c/7cff0dc6-5455-4dea-940b-dff7fe88dc5d.jpg?1576382069","png":"https://img.scryfall.com/cards/png/front/7/c/7cff0dc6-5455-4dea-940b-dff7fe88dc5d.png?1576382069","art_crop":"https://img.scryfall.com/cards/art_crop/front/7/c/7cff0dc6-5455-4dea-940b-dff7fe88dc5d.jpg?1576382069","border_crop":"https://img.scryfall.com/cards/border_crop/front/7/c/7cff0dc6-5455-4dea-940b-dff7fe88dc5d.jpg?1576382069"},"mana_cost":"{2}{G}","cmc":3.0,"type_line":"Legendary Creature — Elf Druid","oracle_text":"When Rishkar, Peema Renegade enters the battlefield, put a +1/+1 counter on each of up to two target creatures.\nEach creature you control with a counter on it has \"{T}: Add {G}.\"","colors":["G"],"color_identity":["G"],"legalities":{"standard":"not_legal","future":"not_legal","historic":"not_legal","pioneer":"legal","modern":"legal","legacy":"legal","pauper":"not_legal","vintage":"legal","penny":"not_legal","commander":"legal","brawl":"not_legal","duel":"legal","oldschool":"not_legal"},"games":["paper","mtgo"],"set":"aer","set_name":"Aether Revolt","set_type":"expansion","set_uri":"https://api.scryfall.com/sets/a4a0db50-8826-4e73-833c-3fd934375f96","set_search_uri":"https://api.scryfall.com/cards/search?order=set&q=e%3Aaer&unique=prints","scryfall_set_uri":"https://scryfall.com/sets/aer?utm_source=api","rulings_uri":"https://api.scryfall.com/cards/7cff0dc6-5455-4dea-940b-dff7fe88dc5d/rulings","prints_search_uri":"https://api.scryfall.com/cards/search?order=released&q=oracleid%3A761021ce-4559-464e-aa03-85c2fe78e267&unique=prints","rarity":"rare","card_back_id":"0aeebaf5-8c7d-4636-9e82-8c27447861f7","artist":"Todd Lockwood","artist_ids":["d0b9f3cc-13fb-42b6-bc43-b034728e5c7b"],"illustration_id":"45fc4489-40d3-495c-995f-f025684d573c","border_color":"black","frame":"2015","edhrec_rank":673,"related_uris":{"tcgplayer_decks":"https://decks.tcgplayer.com/magic/deck/search?contains=Rishkar%2C+Peema+Renegade&page=1&partner=Scryfall&utm_campaign=affiliate&utm_medium=api&utm_source=scryfall","edhrec":"https://edhrec.com/route/?cc=Rishkar%2C+Peema+Renegade","mtgtop8":"https://mtgtop8.com/search?MD_check=1&SB_check=1&cards=Rishkar%2C+Peema+Renegade"}}