{"object":"card","id":"cd42576b-9de5-4d77-9d30-1ef5b5a4fd73","oracle_id":"91f34686-cb96-49c0-b4a7-49dd1fd076e2","multiverse_ids":[407687],"tcgplayer_id":110802,"name":"Sea Gate Wreckage","lang":"en","released_at":"2016-01-22","uri":"https://api.scryfall.com/cards/cd42576b-9de5-4d77-9d30-1ef5b5a4fd73","scryfall_uri":"https://scryfall.com/card/ogw/177/sea-gate-wreckage?utm_source=api","layout":"normal","image_uris":{"small":"https://img.scryfall.com/cards/small/front/c/d/cd42576b-9de5-4d77-9d30-1ef5b5a4fd73.jpg?1562936234","normal":"https://img.scryfall.com/cards/normal/front/c/d/cd42576b-9de5-4d77-9d30-1ef5b5a4fd73.jpg?1562936234","large":"https://img.scryfall.com/cards/large/front/c/d/cd42576b-9de5-4d77-9d30-1ef5b5a4fd73.jpg?1562936234","png":"https://img.scryfall.com/cards/png/front/c/d/cd42576b-9de5-4d77-9d30-1ef5b5a4fd73.png?1562936234","art_crop":"https://img.scryfall.com/cards/art_crop/front/c/d/cd42576b-9de5-4d77-9d30-1ef5b5a4fd73.jpg?1562936234","border_crop":"https://img.scryfall.com/cards/border_crop/front/c/d/cd42576b-9de5-4d77-9d30-1ef5b5a4fd73.jpg?1562936234"},"mana_cost":"","cmc":0.0,"type_line":"Land","oracle_text":"{T}: Add {C}. ({C} represents colorless mana.)\n{2}{C}, {T}: Draw a card. Activate this ability only if you have no cards in hand.","colors":[],"color_identity":[],"legalities":{"standard":"not_legal","future":"not_legal","historic":"not_legal","pioneer":"legal","modern":"legal","legacy":"legal","pauper":"not_legal","vintage":"legal","penny":"not_legal","commander":"legal","brawl":"not_legal","duel":"legal","oldschool":"not_legal"},"games":["paper","mtgo"],"set":"ogw","set_name":"Oath of the Gatewatch","set_type":"expansion","set_uri":"https://api.scryfall.com/sets/cd51d245-8f95-45b0-ab5f-e2b3a3eb5dfe","set_search_uri":"https://api.scryfall.com/cards/search?order=set&q=e%3Aogw&unique=prints","scryfall_set_uri":"https://scryfall.com/sets/ogw?utm_source=api","rulings_uri":"https://api.scryfall.com/cards/cd42576b-9de5-4d77-9d30-1ef5b5a4fd73/rulings","prints_search_uri":"https://api.scryfall.com/cards/search?order=released&q=oracleid%3A91f34686-cb96-49c0-b4a7-49dd1fd076e2&unique=prints","rarity":"rare","card_back_id":"0aeebaf5-8c7d-4636-9e82-8c27447861f7","artist":"Zack Stella","artist_ids":["17bc7f55-958b-43f4-bb40-09746d05b3f9"],"illustration_id":"bd7a866e-9605-42d3-a89b-cac0acd6b5d3","border_color":"black","frame":"2015","edhrec_rank":1926,"related_uris":{"tcgplayer_decks":"https://decks.tcgplayer.com/magic/deck/search?contains=Sea+Gate+Wreckage&page=1&partner=Scryfall&utm_campaign=affiliate&utm_medium=api&utm_source=scryfall","edhrec":"https://edhrec.com/route/?cc=Sea+Gate+Wreckage","mtgtop8":"https://mtgtop8.com/search?MD_check=1&SB_check=1&cards=Sea+Gate+Wreckage"}}