{"object":"card","id":"4ffd5c52-f260-400c-b088-8792282509a5","oracle_id":"3ba50802-57d0-450e-9e2f-a46a09d2f6bb","multiverse_ids":[34205],"tcgplayer_id":10290,"name":"Seedtime","lang":"en","released_at":"2002-05-27","uri":"https://api.scryfall.com/cards/4ffd5c52-f260-400c-b088-8792282509a5","scryfall_uri":"https://scryfall.com/card/jud/130/seedtime?utm_source=api","layout":"normal","image_uris":{"small":"https://img.scryfall.com/cards/small/front/4/f/4ffd5c52-f260-400c-b088-8792282509a5.jpg?1562629836","normal":"https://img.scryfall.com/cards/normal/front/4/f/4ffd5c52-f260-400c-b088-8792282509a5.jpg?1562629836","large":"https://img.scryfall.com/cards/large/front/4/f/4ffd5c52-f260-400c-b088-8792282509a5.jpg?1562629836","png":"https://img.scryfall.com/cards/png/front/4/f/4ffd5c52-f260-400c-b088-8792282509a5.png?1562629836","art_crop":"https://img.scryfall.com/cards/art_crop/front/4/f/4ffd5c52-f260-400c-b088-8792282509a5.jpg?1562629836","border_crop":"https://img.scryfall.com/cards/border_crop/front/4/f/4ffd5c52-f260-400c-b088-8792282509a5.jpg?1562629836"},"mana_cost":"{1}{G}","cmc":2.0,"type_line":"Instant","oracle_text":"Cast this spell only during your turn.\nTake an extra turn after this one if an opponent cast a blue spell this turn.","colors":["G"],"color_identity":["G"],"legalities":{"standard":"not_legal","future":"not_legal","historic":"not_legal","pioneer":"not_legal","modern":"not_legal","legacy":"legal","pauper":"not_legal","vintage":"legal","penny":"not_legal","commander":"legal","brawl":"not_legal","duel":"legal","oldschool":"not_legal"},"games":["paper","mtgo"],"set":"jud","set_name":"Judgment","set_type":"expansion","set_uri":"https://api.scryfall.com/sets/cd82de1a-36fd-4618-bfe8-b45532a582d9","set_search_uri":"https://api.scryfall.com/cards/search?order=set&q=e%3Ajud&unique=prints","scryfall_set_uri":"https://scryfall.com/sets/jud?utm_source=api","rulings_uri":"https://api.scryfall.com/cards/4ffd5c52-f260-400c-b088-8792282509a5/rulings","prints_search_uri":"https://api.scryfall.com/cards/search?order=released&q=oracleid%3A3ba50802-57d0-450e-9e2f-a46a09d2f6bb&unique=prints","rarity":"rare","card_back_id":"0aeebaf5-8c7d-4636-9e82-8c27447861f7","artist":"Rebecca Guay","artist_ids":["f8f662fa-d597-46a3-afb2-91d6e13243e2"],"illustration_id":"7a287768-48ff-48b2-bb59-2a9ad394a066","border_color":"black","frame":"1997","edhrec_rank":7367,"related_uris":{"tcgplayer_decks":"https://decks.tcgplayer.com/magic/deck/search?contains=Seedtime&page=1&partner=Scryfall&utm_campaign=affiliate&utm_medium=api&utm_source=scryfall","edhrec":"https://edhrec.com/route/?cc=Seedtime","mtgtop8":"https://mtgtop8.com/search?MD_check=1&SB_check=1&cards=Seedtime"}}