{"object":"card","id":"ab242eab-5cab-41a0-bcf8-93a6919e4558","oracle_id":"dad3b459-725e-4bf5-bf7a-bd89866ea8c4","multiverse_ids":[10573],"tcgplayer_id":552,"name":"Trained Cheetah","lang":"en","released_at":"1999-05-01","uri":"https://api.scryfall.com/cards/ab242eab-5cab-41a0-bcf8-93a6919e4558","scryfall_uri":"https://scryfall.com/card/ptk/154/trained-cheetah?utm_source=api","layout":"normal","image_uris":{"small":"https://img.scryfall.com/cards/small/front/a/b/ab242eab-5cab-41a0-bcf8-93a6919e4558.jpg?1562257518","normal":"https://img.scryfall.com/cards/normal/front/a/b/ab242eab-5cab-41a0-bcf8-93a6919e4558.jpg?1562257518","large":"https://img.scryfall.com/cards/large/front/a/b/ab242eab-5cab-41a0-bcf8-93a6919e4558.jpg?1562257518","png":"https://img.scryfall.com/cards/png/front/a/b/ab242eab-5cab-41a0-bcf8-93a6919e4558.png?1562257518","art_crop":"https://img.scryfall.com/cards/art_crop/front/a/b/ab242eab-5cab-41a0-bcf8-93a6919e4558.jpg?1562257518","border_crop":"https://img.scryfall.com/cards/border_crop/front/a/b/ab242eab-5cab-41a0-bcf8-93a6919e4558.jpg?1562257518"},"mana_cost":"{2}{G}","cmc":3.0,"type_line":"Creature — Cat","oracle_text":"Whenever Trained Cheetah becomes blocked, it gets +1/+1 until end of turn.","colors":["G"],"color_identity":["G"],"legalities":{"standard":"not_legal","future":"not_legal","historic":"not_legal","pioneer":"not_legal","modern":"not_legal","legacy":"legal","pauper":"not_legal","vintage":"legal","penny":"not_legal","commander":"legal","brawl":"not_legal","duel":"legal","oldschool":"not_legal"},"games":["paper"],"set":"ptk","set_name":"Portal Three Kingdoms","set_type":"starter","set_uri":"https://api.scryfall.com/sets/2676ff2e-9d86-4b5b-b935-e84e41b0755e","set_search_uri":"https://api.scryfall.com/cards/search?order=set&q=e%3Aptk&unique=prints","scryfall_set_uri":"https://scryfall.com/sets/ptk?utm_source=api","rulings_uri":"https://api.scryfall.com/cards/ab242eab-5cab-41a0-bcf8-93a6919e4558/rulings","prints_search_uri":"https://api.scryfall.com/cards/search?order=released&q=oracleid%3Adad3b459-725e-4bf5-bf7a-bd89866ea8c4&unique=prints","rarity":"uncommon","card_back_id":"0aeebaf5-8c7d-4636-9e82-8c27447861f7","artist":"Fang Yue","artist_ids":["b97f06c4-f977-4896-a676-c7dcd3d30842"],"illustration_id":"2865b131-dd74-446a-94f7-35b087b47871","border_color":"white","frame":"1997","edhrec_rank":18719,"related_uris":{"tcgplayer_decks":"https://decks.tcgplayer.com/magic/deck/search?contains=Trained+Cheetah&page=1&partner=Scryfall&utm_campaign=affiliate&utm_medium=api&utm_source=scryfall","edhrec":"https://edhrec.com/route/?cc=Trained+Cheetah","mtgtop8":"https://mtgtop8.com/search?MD_check=1&SB_check=1&cards=Trained+Cheetah"}}