{"object":"card","id":"bce63d86-8748-428a-aa9c-d3c0526537a2","oracle_id":"f4ff3efb-c9ed-4451-a7f2-5ff52ffb6cab","multiverse_ids":[4741],"tcgplayer_id":5786,"name":"Volrath's Curse","lang":"en","released_at":"1997-10-14","uri":"https://api.scryfall.com/cards/bce63d86-8748-428a-aa9c-d3c0526537a2","scryfall_uri":"https://scryfall.com/card/tmp/101/volraths-curse?utm_source=api","layout":"normal","image_uris":{"small":"https://img.scryfall.com/cards/small/front/b/c/bce63d86-8748-428a-aa9c-d3c0526537a2.jpg?1562056380","normal":"https://img.scryfall.com/cards/normal/front/b/c/bce63d86-8748-428a-aa9c-d3c0526537a2.jpg?1562056380","large":"https://img.scryfall.com/cards/large/front/b/c/bce63d86-8748-428a-aa9c-d3c0526537a2.jpg?1562056380","png":"https://img.scryfall.com/cards/png/front/b/c/bce63d86-8748-428a-aa9c-d3c0526537a2.png?1562056380","art_crop":"https://img.scryfall.com/cards/art_crop/front/b/c/bce63d86-8748-428a-aa9c-d3c0526537a2.jpg?1562056380","border_crop":"https://img.scryfall.com/cards/border_crop/front/b/c/bce63d86-8748-428a-aa9c-d3c0526537a2.jpg?1562056380"},"mana_cost":"{1}{U}","cmc":2.0,"type_line":"Enchantment — Aura","oracle_text":"Enchant creature\nEnchanted creature can't attack or block, and its activated abilities can't be activated. That creature's controller may sacrifice a permanent for that player to ignore this effect until end of turn.\n{1}{U}: Return Volrath's Curse to its owner's hand.","colors":["U"],"color_identity":["U"],"legalities":{"standard":"not_legal","future":"not_legal","historic":"not_legal","pioneer":"not_legal","modern":"not_legal","legacy":"legal","pauper":"legal","vintage":"legal","penny":"not_legal","commander":"legal","brawl":"not_legal","duel":"legal","oldschool":"not_legal"},"games":["paper","mtgo"],"set":"tmp","set_name":"Tempest","set_type":"expansion","set_uri":"https://api.scryfall.com/sets/10df3a67-178e-4363-8668-34f0e6edf2a7","set_search_uri":"https://api.scryfall.com/cards/search?order=set&q=e%3Atmp&unique=prints","scryfall_set_uri":"https://scryfall.com/sets/tmp?utm_source=api","rulings_uri":"https://api.scryfall.com/cards/bce63d86-8748-428a-aa9c-d3c0526537a2/rulings","prints_search_uri":"https://api.scryfall.com/cards/search?order=released&q=oracleid%3Af4ff3efb-c9ed-4451-a7f2-5ff52ffb6cab&unique=prints","rarity":"common","card_back_id":"0aeebaf5-8c7d-4636-9e82-8c27447861f7","artist":"Daren Bader","artist_ids":["7da1a585-c875-45e4-b322-5da9e8e1f651"],"illustration_id":"2309237c-18f4-4578-a120-a73ed9267375","border_color":"black","frame":"1997","edhrec_rank":12575,"related_uris":{"tcgplayer_decks":"https://decks.tcgplayer.com/magic/deck/search?contains=Volrath%27s+Curse&page=1&partner=Scryfall&utm_campaign=affiliate&utm_medium=api&utm_source=scryfall","edhrec":"https://edhrec.com/route/?cc=Volrath%27s+Curse","mtgtop8":"https://mtgtop8.com/search?MD_check=1&SB_check=1&cards=Volrath%27s+Curse"}}