{"object":"card","id":"c2571ff7-0287-4ba2-8365-5ff08de641a2","oracle_id":"bb4ab425-3da7-455d-b217-3d585d476113","multiverse_ids":[6156],"tcgplayer_id":4432,"name":"Workhorse","lang":"en","released_at":"1998-06-15","uri":"https://api.scryfall.com/cards/c2571ff7-0287-4ba2-8365-5ff08de641a2","scryfall_uri":"https://scryfall.com/card/exo/142/workhorse?utm_source=api","layout":"normal","image_uris":{"small":"https://img.scryfall.com/cards/small/front/c/2/c2571ff7-0287-4ba2-8365-5ff08de641a2.jpg?1562088789","normal":"https://img.scryfall.com/cards/normal/front/c/2/c2571ff7-0287-4ba2-8365-5ff08de641a2.jpg?1562088789","large":"https://img.scryfall.com/cards/large/front/c/2/c2571ff7-0287-4ba2-8365-5ff08de641a2.jpg?1562088789","png":"https://img.scryfall.com/cards/png/front/c/2/c2571ff7-0287-4ba2-8365-5ff08de641a2.png?1562088789","art_crop":"https://img.scryfall.com/cards/art_crop/front/c/2/c2571ff7-0287-4ba2-8365-5ff08de641a2.jpg?1562088789","border_crop":"https://img.scryfall.com/cards/border_crop/front/c/2/c2571ff7-0287-4ba2-8365-5ff08de641a2.jpg?1562088789"},"mana_cost":"{6}","cmc":6.0,"type_line":"Artifact Creature — Horse","oracle_text":"Workhorse enters the battlefield with four +1/+1 counters on it.\nRemove a +1/+1 counter from Workhorse: Add {C}.","colors":[],"color_identity":[],"legalities":{"standard":"not_legal","future":"not_legal","historic":"not_legal","pioneer":"not_legal","modern":"not_legal","legacy":"legal","pauper":"not_legal","vintage":"legal","penny":"not_legal","commander":"legal","brawl":"not_legal","duel":"legal","oldschool":"not_legal"},"games":["paper","mtgo"],"set":"exo","set_name":"Exodus","set_type":"expansion","set_uri":"https://api.scryfall.com/sets/1401f7af-2e71-476d-9813-991084ed0bb9","set_search_uri":"https://api.scryfall.com/cards/search?order=set&q=e%3Aexo&unique=prints","scryfall_set_uri":"https://scryfall.com/sets/exo?utm_source=api","rulings_uri":"https://api.scryfall.com/cards/c2571ff7-0287-4ba2-8365-5ff08de641a2/rulings","prints_search_uri":"https://api.scryfall.com/cards/search?order=released&q=oracleid%3Abb4ab425-3da7-455d-b217-3d585d476113&unique=prints","rarity":"rare","card_back_id":"0aeebaf5-8c7d-4636-9e82-8c27447861f7","artist":"DiTerlizzi","artist_ids":["ed44dce4-30cf-4c2c-b2e1-a19ba2295690"],"illustration_id":"4bc8e9d2-62a9-46b6-85db-eb7f0df8d6c0","border_color":"black","frame":"1997","edhrec_rank":6211,"related_uris":{"tcgplayer_decks":"https://decks.tcgplayer.com/magic/deck/search?contains=Workhorse&page=1&partner=Scryfall&utm_campaign=affiliate&utm_medium=api&utm_source=scryfall","edhrec":"https://edhrec.com/route/?cc=Workhorse","mtgtop8":"https://mtgtop8.com/search?MD_check=1&SB_check=1&cards=Workhorse"}}